Workbook

Sheet Entradas
A1: Calculadora de ROI do Growth Stack
A2: Preencha as células brancas. As demais são calculadas. Use números que você possa defender.
A5: Visitas mensais da página | B5: 3000 | C5: Dado do analytics — não estime.
A6: Taxa de conversão atual | B6: 0.012 | C6: Conversões / visitas. Se não mede, use 0,5% como ponto de partida conservador.
A7: Ticket médio (R$) | B7: 1200 | C7: Receita média por conversão.
A8: Margem bruta (%) | B8: 0.6 | C8: Parte da receita que sobra depois do custo direto de entrega.
A9: Horas de trabalho por projeto | B9: 12 | C9: Tempo humano real gasto no funil completo.
A10: Valor da sua hora (R$) | B10: 120 | C10: Se você não sabe, use o valor que cobraria por consultoria.
A11: Custo mensal das APIs (R$) | B11: 150 | C11: Da aba Custos do Growth Stack Dashboard.

Sheet Cenários
A1: Cenários de resultado
A2: Três hipóteses de melhora de conversão. O cenário conservador é o único que você pode apresentar como expectativa.
A4: Indicador | B4: Conservador | C4: Base | D4: Otimista
B5: 1.15 | C5: 1.4 | D5: 1.75
A6: Nova taxa de conversão | B6: =Entradas!$B$6*B5 | C6: =Entradas!$B$6*C5 | D6: =Entradas!$B$6*D5
A7: Conversões atuais/mês | B7: =Entradas!$B$5*Entradas!$B$6 | C7: =Entradas!$B$5*Entradas!$B$6 | D7: =Entradas!$B$5*Entradas!$B$6
A8: Conversões novas/mês | B8: =Entradas!$B$5*B5 | C8: =Entradas!$B$5*C5 | D8: =Entradas!$B$5*D5
A9: Receita atual/mês | B9: =Entradas!$B$5*Entradas!$B$6*Entradas!$B$7 | C9: =Entradas!$B$5*Entradas!$B$6*Entradas!$B$7 | D9: =Entradas!$B$5*Entradas!$B$6*Entradas!$B$7
A10: Receita nova/mês | B10: =Entradas!$B$5*B5*Entradas!$B$7 | C10: =Entradas!$B$5*C5*Entradas!$B$7 | D10: =Entradas!$B$5*D5*Entradas!$B$7
A11: Receita adicional/mês | B11: =B10-B9 | C11: =C10-C9 | D11: =D10-D9
A12: Margem sobre o adicional | B12: =B11*Entradas!$B$8 | C12: =C11*Entradas!$B$8 | D12: =D11*Entradas!$B$8
A13: Custo do projeto (horas + APIs) | B13: =Entradas!$B$9*Entradas!$B$10+Entradas!$B$11 | C13: =Entradas!$B$9*Entradas!$B$10+Entradas!$B$11 | D13: =Entradas!$B$9*Entradas!$B$10+Entradas!$B$11
A14: Resultado no 1º mês | B14: =B12-B13 | C14: =C12-C13 | D14: =D12-D13
A15: ROI no 1º mês | B15: =IFERROR(B14/B13,0) | C15: =IFERROR(C14/C13,0) | D15: =IFERROR(D14/D13,0)
A16: Payback (meses) | B16: =IFERROR(B13/B12,0) | C16: =IFERROR(C13/C12,0) | D16: =IFERROR(D13/D12,0)

Sheet Custos API
A1: Custo das APIs
A2: Estime por projeto antes de propor o preço ao cliente. Revise mensalmente.
A4: API | B4: Chamadas por projeto | C4: Custo unitário | D4: Custo no projeto | E4: Observação
A5: Website Data Extraction | B5: 1 | D5: =B5*C5
A6: AI SEO Analysis | B6: 1 | D6: =B6*C6
A7: AI Conversion Optimization | B7: 1 | D7: =B7*C7
A8: AI Website Copywriter | B8: 1 | D8: =B8*C8
A9: AI Landing Page Optimizer | B9: 1 | D9: =B9*C9
A10: AI Social Media Generator | B10: 1 | D10: =B10*C10
C13: TOTAL | D13: =SUM(D5:D10)

Sheet Como usar
B2: Como usar esta calculadora
A4: 1. | B4: Preencha a aba Entradas com dados do SEU projeto. Se não tiver o número, não invente — meça ou use o ponto de partida conservador indicado.
A5: 2. | B5: Na aba Cenários, ajuste apenas os multiplicadores (1,15x / 1,40x / 1,75x). Eles representam o quanto a taxa de conversão melhora depois do trabalho.
A6: 3. | B6: O cenário conservador é o único que pode ser apresentado ao cliente como expectativa. Os outros dois servem para você decidir se vale aceitar o projeto.
A7: 4. | B7: Se o payback for maior que 3 meses no cenário conservador, o projeto provavelmente não fecha — reduza escopo, aumente ticket ou escolha outro cliente.
A9: Importante. | B9: Isto é uma ferramenta de decisão, não uma previsão. Melhora de conversão depende de oferta, público, tráfego e execução. Nunca apresente estes números como garantia.
A10: Ética. | B10: Se você usar esta planilha com um cliente, deixe claro que os valores são cenários hipotéticos construídos a partir de dados que ele forneceu.
